[
 {
  "Location": "AHMEDABAD",
  "Index": 1,
  "Social Category": "General",
  "Girls_1": 3.28,
  "Boys_1": 1.99,
  "Overall_1": 2.57,
  "Girls_2": 6.29,
  "Boys_2": 1.07,
  "Overall_2": 3.39,
  "Girls_3": 14.29,
  "Boys_3": 15.27,
  "Overall_3": 14.85
 },
 {
  "Location": "AHMEDABAD",
  "Index": 2,
  "Social Category": "OBC",
  "Girls_1": 5.88,
  "Boys_1": 1.81,
  "Overall_1": 3.74,
  "Girls_2": 15.22,
  "Boys_2": 3.05,
  "Overall_2": 8.53,
  "Girls_3": 29.08,
  "Boys_3": 26.58,
  "Overall_3": 27.54
 },
 {
  "Location": "AHMEDABAD",
  "Index": 3,
  "Social Category": "SC",
  "Girls_1": 2.39,
  "Boys_1": 0,
  "Overall_1": 0.84,
  "Girls_2": 3.21,
  "Boys_2": 0,
  "Overall_2": 0,
  "Girls_3": 26.39,
  "Boys_3": 20.96,
  "Overall_3": 23.42
 },
 {
  "Location": "AHMEDABAD",
  "Index": 4,
  "Social Category": "ST",
  "Girls_1": 7.44,
  "Boys_1": 5.39,
  "Overall_1": 6.34,
  "Girls_2": 17.73,
  "Boys_2": 19.08,
  "Overall_2": 18.52,
  "Girls_3": 39.66,
  "Boys_3": 41.65,
  "Overall_3": 40.87
 },
 {
  "Location": "AHMEDABAD",
  "Index": 5,
  "Social Category": "Overall",
  "Girls_1": 4.46,
  "Boys_1": 1.74,
  "Overall_1": 3.01,
  "Girls_2": 10.01,
  "Boys_2": 1.55,
  "Overall_2": 5.35,
  "Girls_3": 21.41,
  "Boys_3": 20.75,
  "Overall_3": 21.02
 },
 {
  "Location": "AMRELI",
  "Index": 6,
  "Social Category": "General",
  "Girls_1": 10.67,
  "Boys_1": 7.83,
  "Overall_1": 9.07,
  "Girls_2": 2.99,
  "Boys_2": 6.86,
  "Overall_2": 5.12,
  "Girls_3": 6.16,
  "Boys_3": 14.57,
  "Overall_3": 10.66
 },
 {
  "Location": "AMRELI",
  "Index": 7,
  "Social Category": "OBC",
  "Girls_1": 1.81,
  "Boys_1": 2.53,
  "Overall_1": 2.19,
  "Girls_2": 13.14,
  "Boys_2": 6.46,
  "Overall_2": 9.55,
  "Girls_3": 23.61,
  "Boys_3": 25.77,
  "Overall_3": 24.94
 },
 {
  "Location": "AMRELI",
  "Index": 8,
  "Social Category": "SC",
  "Girls_1": 3.69,
  "Boys_1": 2.87,
  "Overall_1": 3.27,
  "Girls_2": 5.79,
  "Boys_2": 4.61,
  "Overall_2": 5.17,
  "Girls_3": 24.4,
  "Boys_3": 25.86,
  "Overall_3": 25.18
 },
 {
  "Location": "AMRELI",
  "Index": 9,
  "Social Category": "ST",
  "Girls_1": 0,
  "Boys_1": 0.51,
  "Overall_1": 0,
  "Girls_2": 19.82,
  "Boys_2": 8.46,
  "Overall_2": 12.92,
  "Girls_3": 34.37,
  "Boys_3": 10.45,
  "Overall_3": 20.43
 },
 {
  "Location": "AMRELI",
  "Index": 10,
  "Social Category": "Overall",
  "Girls_1": 3.33,
  "Boys_1": 3.53,
  "Overall_1": 3.44,
  "Girls_2": 10.28,
  "Boys_2": 6.37,
  "Overall_2": 8.17,
  "Girls_3": 17.84,
  "Boys_3": 22.53,
  "Overall_3": 20.56
 },
 {
  "Location": "ANAND",
  "Index": 11,
  "Social Category": "General",
  "Girls_1": 2.15,
  "Boys_1": 3.44,
  "Overall_1": 2.86,
  "Girls_2": 3.48,
  "Boys_2": 1.56,
  "Overall_2": 2.41,
  "Girls_3": 17.02,
  "Boys_3": 19.02,
  "Overall_3": 18.18
 },
 {
  "Location": "ANAND",
  "Index": 12,
  "Social Category": "OBC",
  "Girls_1": 0,
  "Boys_1": 0,
  "Overall_1": 0,
  "Girls_2": 10.33,
  "Boys_2": 5.77,
  "Overall_2": 7.77,
  "Girls_3": 26.54,
  "Boys_3": 27.84,
  "Overall_3": 27.37
 },
 {
  "Location": "ANAND",
  "Index": 13,
  "Social Category": "SC",
  "Girls_1": 0,
  "Boys_1": 0,
  "Overall_1": 0,
  "Girls_2": 0,
  "Boys_2": 0,
  "Overall_2": 0,
  "Girls_3": 14.06,
  "Boys_3": 12.82,
  "Overall_3": 13.37
 },
 {
  "Location": "ANAND",
  "Index": 14,
  "Social Category": "ST",
  "Girls_1": 3.77,
  "Boys_1": 0.84,
  "Overall_1": 2.15,
  "Girls_2": 0,
  "Boys_2": 0,
  "Overall_2": 0,
  "Girls_3": 11.45,
  "Boys_3": 19.98,
  "Overall_3": 16.93
 },
 {
  "Location": "ANAND",
  "Index": 15,
  "Social Category": "Overall",
  "Girls_1": 0.34,
  "Boys_1": 0.55,
  "Overall_1": 0.45,
  "Girls_2": 7.18,
  "Boys_2": 3.62,
  "Overall_2": 5.19,
  "Girls_3": 21.79,
  "Boys_3": 23.97,
  "Overall_3": 23.12
 },
 {
  "Location": "ARAVALLI",
  "Index": 16,
  "Social Category": "General",
  "Girls_1": 0,
  "Boys_1": 0,
  "Overall_1": 0,
  "Girls_2": 0,
  "Boys_2": 0,
  "Overall_2": 0,
  "Girls_3": 0,
  "Boys_3": 0,
  "Overall_3": 0
 },
 {
  "Location": "ARAVALLI",
  "Index": 17,
  "Social Category": "OBC",
  "Girls_1": 0,
  "Boys_1": 0,
  "Overall_1": 0,
  "Girls_2": 0,
  "Boys_2": 0,
  "Overall_2": 0,
  "Girls_3": 0,
  "Boys_3": 0,
  "Overall_3": 0
 },
 {
  "Location": "ARAVALLI",
  "Index": 18,
  "Social Category": "SC",
  "Girls_1": 0,
  "Boys_1": 0,
  "Overall_1": 0,
  "Girls_2": 0,
  "Boys_2": 0,
  "Overall_2": 0,
  "Girls_3": 0,
  "Boys_3": 0,
  "Overall_3": 0
 },
 {
  "Location": "ARAVALLI",
  "Index": 19,
  "Social Category": "ST",
  "Girls_1": 0,
  "Boys_1": 0,
  "Overall_1": 0,
  "Girls_2": 0,
  "Boys_2": 0,
  "Overall_2": 0,
  "Girls_3": 0,
  "Boys_3": 0,
  "Overall_3": 0
 },
 {
  "Location": "ARAVALLI",
  "Index": 20,
  "Social Category": "Overall",
  "Girls_1": 0,
  "Boys_1": 0,
  "Overall_1": 0,
  "Girls_2": 0,
  "Boys_2": 0,
  "Overall_2": 0,
  "Girls_3": 0,
  "Boys_3": 0,
  "Overall_3": 0
 },
 {
  "Location": "BANAS KANTHA",
  "Index": 21,
  "Social Category": "General",
  "Girls_1": 2.33,
  "Boys_1": 2.27,
  "Overall_1": 2.31,
  "Girls_2": 13.91,
  "Boys_2": 6.35,
  "Overall_2": 9.69,
  "Girls_3": 22.41,
  "Boys_3": 20.51,
  "Overall_3": 21.22
 },
 {
  "Location": "BANAS KANTHA",
  "Index": 22,
  "Social Category": "OBC",
  "Girls_1": 1.57,
  "Boys_1": 0.82,
  "Overall_1": 1.17,
  "Girls_2": 15.32,
  "Boys_2": 6.6,
  "Overall_2": 10.26,
  "Girls_3": 25.17,
  "Boys_3": 21.78,
  "Overall_3": 22.8
 },
 {
  "Location": "BANAS KANTHA",
  "Index": 23,
  "Social Category": "SC",
  "Girls_1": 2.49,
  "Boys_1": 2.43,
  "Overall_1": 2.46,
  "Girls_2": 13.08,
  "Boys_2": 6.93,
  "Overall_2": 9.72,
  "Girls_3": 28.89,
  "Boys_3": 25.37,
  "Overall_3": 26.65
 },
 {
  "Location": "BANAS KANTHA",
  "Index": 24,
  "Social Category": "ST",
  "Girls_1": 3.62,
  "Boys_1": 3.26,
  "Overall_1": 3.43,
  "Girls_2": 10.01,
  "Boys_2": 11.15,
  "Overall_2": 10.65,
  "Girls_3": 23.6,
  "Boys_3": 27.38,
  "Overall_3": 25.76
 },
 {
  "Location": "BANAS KANTHA",
  "Index": 25,
  "Social Category": "Overall",
  "Girls_1": 2.01,
  "Boys_1": 1.47,
  "Overall_1": 1.72,
  "Girls_2": 14.37,
  "Boys_2": 6.97,
  "Overall_2": 10.15,
  "Girls_3": 24.99,
  "Boys_3": 22.36,
  "Overall_3": 23.23
 },
 {
  "Location": "BHARUCH",
  "Index": 26,
  "Social Category": "General",
  "Girls_1": 0.72,
  "Boys_1": 0,
  "Overall_1": 0.27,
  "Girls_2": 5.44,
  "Boys_2": 1.63,
  "Overall_2": 3.41,
  "Girls_3": 18.89,
  "Boys_3": 25.05,
  "Overall_3": 22.34
 },
 {
  "Location": "BHARUCH",
  "Index": 27,
  "Social Category": "OBC",
  "Girls_1": 4.36,
  "Boys_1": 4.83,
  "Overall_1": 4.61,
  "Girls_2": 10.67,
  "Boys_2": 7.29,
  "Overall_2": 8.83,
  "Girls_3": 25.15,
  "Boys_3": 36.57,
  "Overall_3": 31.75
 },
 {
  "Location": "BHARUCH",
  "Index": 28,
  "Social Category": "SC",
  "Girls_1": 0,
  "Boys_1": 0,
  "Overall_1": 0,
  "Girls_2": 0,
  "Boys_2": 0,
  "Overall_2": 0,
  "Girls_3": 8.07,
  "Boys_3": 30.84,
  "Overall_3": 20.82
 },
 {
  "Location": "BHARUCH",
  "Index": 29,
  "Social Category": "ST",
  "Girls_1": 1.53,
  "Boys_1": 1.48,
  "Overall_1": 1.51,
  "Girls_2": 13.91,
  "Boys_2": 10.52,
  "Overall_2": 12.15,
  "Girls_3": 30.64,
  "Boys_3": 37.93,
  "Overall_3": 34.83
 },
 {
  "Location": "BHARUCH",
  "Index": 30,
  "Social Category": "Overall",
  "Girls_1": 1.24,
  "Boys_1": 1.24,
  "Overall_1": 1.24,
  "Girls_2": 9.09,
  "Boys_2": 5.68,
  "Overall_2": 7.28,
  "Girls_3": 23.04,
  "Boys_3": 31.88,
  "Overall_3": 28.07
 },
 {
  "Location": "BHAVNAGAR",
  "Index": 31,
  "Social Category": "General",
  "Girls_1": 15.1,
  "Boys_1": 15.12,
  "Overall_1": 15.11,
  "Girls_2": 20.76,
  "Boys_2": 15.49,
  "Overall_2": 17.8,
  "Girls_3": 38.05,
  "Boys_3": 37.8,
  "Overall_3": 37.9
 },
 {
  "Location": "BHAVNAGAR",
  "Index": 32,
  "Social Category": "OBC",
  "Girls_1": 18.3,
  "Boys_1": 18.44,
  "Overall_1": 18.37,
  "Girls_2": 27.68,
  "Boys_2": 22.39,
  "Overall_2": 24.79,
  "Girls_3": 36.87,
  "Boys_3": 40.19,
  "Overall_3": 38.99
 },
 {
  "Location": "BHAVNAGAR",
  "Index": 33,
  "Social Category": "SC",
  "Girls_1": 18.71,
  "Boys_1": 20.97,
  "Overall_1": 19.91,
  "Girls_2": 28.11,
  "Boys_2": 29.98,
  "Overall_2": 29.15,
  "Girls_3": 40.77,
  "Boys_3": 40.37,
  "Overall_3": 40.55
 },
 {
  "Location": "BHAVNAGAR",
  "Index": 34,
  "Social Category": "ST",
  "Girls_1": 29.18,
  "Boys_1": 34.62,
  "Overall_1": 32.5,
  "Girls_2": 22.22,
  "Boys_2": 23.03,
  "Overall_2": 22.74,
  "Girls_3": 47.45,
  "Boys_3": 44.7,
  "Overall_3": 45.82
 },
 {
  "Location": "BHAVNAGAR",
  "Index": 35,
  "Social Category": "Overall",
  "Girls_1": 17.95,
  "Boys_1": 18.24,
  "Overall_1": 18.1,
  "Girls_2": 26.46,
  "Boys_2": 21.58,
  "Overall_2": 23.77,
  "Girls_3": 37.59,
  "Boys_3": 39.61,
  "Overall_3": 38.84
 },
 {
  "Location": "BOTAD",
  "Index": 36,
  "Social Category": "General",
  "Girls_1": 0,
  "Boys_1": 0,
  "Overall_1": 0,
  "Girls_2": 0,
  "Boys_2": 0,
  "Overall_2": 0,
  "Girls_3": 0,
  "Boys_3": 0,
  "Overall_3": 0
 },
 {
  "Location": "BOTAD",
  "Index": 37,
  "Social Category": "OBC",
  "Girls_1": 0,
  "Boys_1": 0,
  "Overall_1": 0,
  "Girls_2": 0,
  "Boys_2": 0,
  "Overall_2": 0,
  "Girls_3": 0,
  "Boys_3": 0,
  "Overall_3": 0
 },
 {
  "Location": "BOTAD",
  "Index": 38,
  "Social Category": "SC",
  "Girls_1": 0,
  "Boys_1": 0,
  "Overall_1": 0,
  "Girls_2": 0,
  "Boys_2": 0,
  "Overall_2": 0,
  "Girls_3": 0,
  "Boys_3": 0,
  "Overall_3": 0
 },
 {
  "Location": "BOTAD",
  "Index": 39,
  "Social Category": "ST",
  "Girls_1": 0,
  "Boys_1": 0,
  "Overall_1": 0,
  "Girls_2": 0,
  "Boys_2": 0,
  "Overall_2": 0,
  "Girls_3": 0,
  "Boys_3": 0,
  "Overall_3": 0
 },
 {
  "Location": "BOTAD",
  "Index": 40,
  "Social Category": "Overall",
  "Girls_1": 0,
  "Boys_1": 0,
  "Overall_1": 0,
  "Girls_2": 0,
  "Boys_2": 0,
  "Overall_2": 0,
  "Girls_3": 0,
  "Boys_3": 0,
  "Overall_3": 0
 },
 {
  "Location": "CHHOTAUDEPUR",
  "Index": 41,
  "Social Category": "General",
  "Girls_1": 0,
  "Boys_1": 0,
  "Overall_1": 0,
  "Girls_2": 0,
  "Boys_2": 0,
  "Overall_2": 0,
  "Girls_3": 0,
  "Boys_3": 0,
  "Overall_3": 0
 },
 {
  "Location": "CHHOTAUDEPUR",
  "Index": 42,
  "Social Category": "OBC",
  "Girls_1": 0,
  "Boys_1": 0,
  "Overall_1": 0,
  "Girls_2": 0,
  "Boys_2": 0,
  "Overall_2": 0,
  "Girls_3": 0,
  "Boys_3": 0,
  "Overall_3": 0
 },
 {
  "Location": "CHHOTAUDEPUR",
  "Index": 43,
  "Social Category": "SC",
  "Girls_1": 0,
  "Boys_1": 0,
  "Overall_1": 0,
  "Girls_2": 0,
  "Boys_2": 0,
  "Overall_2": 0,
  "Girls_3": 0,
  "Boys_3": 0,
  "Overall_3": 0
 },
 {
  "Location": "CHHOTAUDEPUR",
  "Index": 44,
  "Social Category": "ST",
  "Girls_1": 0,
  "Boys_1": 0,
  "Overall_1": 0,
  "Girls_2": 0,
  "Boys_2": 0,
  "Overall_2": 0,
  "Girls_3": 0,
  "Boys_3": 0,
  "Overall_3": 0
 },
 {
  "Location": "CHHOTAUDEPUR",
  "Index": 45,
  "Social Category": "Overall",
  "Girls_1": 0,
  "Boys_1": 0,
  "Overall_1": 0,
  "Girls_2": 0,
  "Boys_2": 0,
  "Overall_2": 0,
  "Girls_3": 0,
  "Boys_3": 0,
  "Overall_3": 0
 },
 {
  "Location": "DEVBHOOMI DWARKA",
  "Index": 46,
  "Social Category": "General",
  "Girls_1": 0,
  "Boys_1": 0,
  "Overall_1": 0,
  "Girls_2": 0,
  "Boys_2": 0,
  "Overall_2": 0,
  "Girls_3": 0,
  "Boys_3": 0,
  "Overall_3": 0
 },
 {
  "Location": "DEVBHOOMI DWARKA",
  "Index": 47,
  "Social Category": "OBC",
  "Girls_1": 0,
  "Boys_1": 0,
  "Overall_1": 0,
  "Girls_2": 0,
  "Boys_2": 0,
  "Overall_2": 0,
  "Girls_3": 0,
  "Boys_3": 0,
  "Overall_3": 0
 },
 {
  "Location": "DEVBHOOMI DWARKA",
  "Index": 48,
  "Social Category": "SC",
  "Girls_1": 0,
  "Boys_1": 0,
  "Overall_1": 0,
  "Girls_2": 0,
  "Boys_2": 0,
  "Overall_2": 0,
  "Girls_3": 0,
  "Boys_3": 0,
  "Overall_3": 0
 },
 {
  "Location": "DEVBHOOMI DWARKA",
  "Index": 49,
  "Social Category": "ST",
  "Girls_1": 0,
  "Boys_1": 0,
  "Overall_1": 0,
  "Girls_2": 0,
  "Boys_2": 0,
  "Overall_2": 0,
  "Girls_3": 0,
  "Boys_3": 0,
  "Overall_3": 0
 },
 {
  "Location": "DEVBHOOMI DWARKA",
  "Index": 50,
  "Social Category": "Overall",
  "Girls_1": 0,
  "Boys_1": 0,
  "Overall_1": 0,
  "Girls_2": 0,
  "Boys_2": 0,
  "Overall_2": 0,
  "Girls_3": 0,
  "Boys_3": 0,
  "Overall_3": 0
 },
 {
  "Location": "DOHAD",
  "Index": 51,
  "Social Category": "General",
  "Girls_1": 6.75,
  "Boys_1": 9.3,
  "Overall_1": 8.15,
  "Girls_2": 6.38,
  "Boys_2": 5.31,
  "Overall_2": 5.8,
  "Girls_3": 56.65,
  "Boys_3": 43.54,
  "Overall_3": 50.27
 },
 {
  "Location": "DOHAD",
  "Index": 52,
  "Social Category": "OBC",
  "Girls_1": 2.17,
  "Boys_1": 4.77,
  "Overall_1": 3.53,
  "Girls_2": 4.7,
  "Boys_2": 4.85,
  "Overall_2": 4.78,
  "Girls_3": 19.14,
  "Boys_3": 21.9,
  "Overall_3": 20.59
 },
 {
  "Location": "DOHAD",
  "Index": 53,
  "Social Category": "SC",
  "Girls_1": 0,
  "Boys_1": 0,
  "Overall_1": 0,
  "Girls_2": 0,
  "Boys_2": 0,
  "Overall_2": 0,
  "Girls_3": 28.65,
  "Boys_3": 29.03,
  "Overall_3": 28.83
 },
 {
  "Location": "DOHAD",
  "Index": 54,
  "Social Category": "ST",
  "Girls_1": 5.93,
  "Boys_1": 6.25,
  "Overall_1": 6.1,
  "Girls_2": 13.75,
  "Boys_2": 12.3,
  "Overall_2": 12.99,
  "Girls_3": 23.56,
  "Boys_3": 24.83,
  "Overall_3": 24.22
 },
 {
  "Location": "DOHAD",
  "Index": 55,
  "Social Category": "Overall",
  "Girls_1": 4.81,
  "Boys_1": 5.43,
  "Overall_1": 5.13,
  "Girls_2": 11.09,
  "Boys_2": 10.19,
  "Overall_2": 10.61,
  "Girls_3": 24.47,
  "Boys_3": 25.13,
  "Overall_3": 24.81
 },
 {
  "Location": "GANDHINAGAR",
  "Index": 56,
  "Social Category": "General",
  "Girls_1": 1.07,
  "Boys_1": 0.12,
  "Overall_1": 0.52,
  "Girls_2": 0.66,
  "Boys_2": 0,
  "Overall_2": 0.25,
  "Girls_3": 9.19,
  "Boys_3": 13.88,
  "Overall_3": 12.13
 },
 {
  "Location": "GANDHINAGAR",
  "Index": 57,
  "Social Category": "OBC",
  "Girls_1": 0.52,
  "Boys_1": 0,
  "Overall_1": 0.06,
  "Girls_2": 8.52,
  "Boys_2": 0.3,
  "Overall_2": 3.86,
  "Girls_3": 27.44,
  "Boys_3": 25,
  "Overall_3": 25.86
 },
 {
  "Location": "GANDHINAGAR",
  "Index": 58,
  "Social Category": "SC",
  "Girls_1": 0,
  "Boys_1": 0,
  "Overall_1": 0,
  "Girls_2": 0.64,
  "Boys_2": 1.26,
  "Overall_2": 1,
  "Girls_3": 15.61,
  "Boys_3": 20.89,
  "Overall_3": 18.73
 },
 {
  "Location": "GANDHINAGAR",
  "Index": 59,
  "Social Category": "ST",
  "Girls_1": 9.88,
  "Boys_1": 5.25,
  "Overall_1": 7.18,
  "Girls_2": 4.71,
  "Boys_2": 6.22,
  "Overall_2": 5.64,
  "Girls_3": 1.8,
  "Boys_3": 0,
  "Overall_3": 0
 },
 {
  "Location": "GANDHINAGAR",
  "Index": 60,
  "Social Category": "Overall",
  "Girls_1": 0.71,
  "Boys_1": 0,
  "Overall_1": 0.22,
  "Girls_2": 5.77,
  "Boys_2": 0.49,
  "Overall_2": 2.68,
  "Girls_3": 19.06,
  "Boys_3": 20.17,
  "Overall_3": 19.77
 },
 {
  "Location": "GIR SOMNATH",
  "Index": 61,
  "Social Category": "General",
  "Girls_1": 0,
  "Boys_1": 0,
  "Overall_1": 0,
  "Girls_2": 0,
  "Boys_2": 0,
  "Overall_2": 0,
  "Girls_3": 0,
  "Boys_3": 0,
  "Overall_3": 0
 },
 {
  "Location": "GIR SOMNATH",
  "Index": 62,
  "Social Category": "OBC",
  "Girls_1": 0,
  "Boys_1": 0,
  "Overall_1": 0,
  "Girls_2": 0,
  "Boys_2": 0,
  "Overall_2": 0,
  "Girls_3": 0,
  "Boys_3": 0,
  "Overall_3": 0
 },
 {
  "Location": "GIR SOMNATH",
  "Index": 63,
  "Social Category": "SC",
  "Girls_1": 0,
  "Boys_1": 0,
  "Overall_1": 0,
  "Girls_2": 0,
  "Boys_2": 0,
  "Overall_2": 0,
  "Girls_3": 0,
  "Boys_3": 0,
  "Overall_3": 0
 },
 {
  "Location": "GIR SOMNATH",
  "Index": 64,
  "Social Category": "ST",
  "Girls_1": 0,
  "Boys_1": 0,
  "Overall_1": 0,
  "Girls_2": 0,
  "Boys_2": 0,
  "Overall_2": 0,
  "Girls_3": 0,
  "Boys_3": 0,
  "Overall_3": 0
 },
 {
  "Location": "GIR SOMNATH",
  "Index": 65,
  "Social Category": "Overall",
  "Girls_1": 0,
  "Boys_1": 0,
  "Overall_1": 0,
  "Girls_2": 0,
  "Boys_2": 0,
  "Overall_2": 0,
  "Girls_3": 0,
  "Boys_3": 0,
  "Overall_3": 0
 },
 {
  "Location": "JAMNAGAR",
  "Index": 66,
  "Social Category": "General",
  "Girls_1": 20.45,
  "Boys_1": 17.26,
  "Overall_1": 18.68,
  "Girls_2": 18.98,
  "Boys_2": 18.18,
  "Overall_2": 18.53,
  "Girls_3": 28.2,
  "Boys_3": 36.53,
  "Overall_3": 32.88
 },
 {
  "Location": "JAMNAGAR",
  "Index": 67,
  "Social Category": "OBC",
  "Girls_1": 44.92,
  "Boys_1": 43.34,
  "Overall_1": 44.1,
  "Girls_2": 53.06,
  "Boys_2": 47.42,
  "Overall_2": 50.05,
  "Girls_3": 54.73,
  "Boys_3": 61.42,
  "Overall_3": 58.9
 },
 {
  "Location": "JAMNAGAR",
  "Index": 68,
  "Social Category": "SC",
  "Girls_1": 28.44,
  "Boys_1": 30.57,
  "Overall_1": 29.54,
  "Girls_2": 35.39,
  "Boys_2": 32.21,
  "Overall_2": 33.72,
  "Girls_3": 48.62,
  "Boys_3": 53.6,
  "Overall_3": 51.5
 },
 {
  "Location": "JAMNAGAR",
  "Index": 69,
  "Social Category": "ST",
  "Girls_1": 3.46,
  "Boys_1": 0.66,
  "Overall_1": 1.72,
  "Girls_2": 20.79,
  "Boys_2": 13.86,
  "Overall_2": 16.59,
  "Girls_3": 34.4,
  "Boys_3": 45.67,
  "Overall_3": 41.95
 },
 {
  "Location": "JAMNAGAR",
  "Index": 70,
  "Social Category": "Overall",
  "Girls_1": 37.55,
  "Boys_1": 35.05,
  "Overall_1": 36.23,
  "Girls_2": 42.86,
  "Boys_2": 38.05,
  "Overall_2": 40.26,
  "Girls_3": 44.11,
  "Boys_3": 52.58,
  "Overall_3": 49.18
 },
 {
  "Location": "JUNAGADH",
  "Index": 71,
  "Social Category": "General",
  "Girls_1": 36.15,
  "Boys_1": 32.95,
  "Overall_1": 34.35,
  "Girls_2": 37.21,
  "Boys_2": 30.76,
  "Overall_2": 33.51,
  "Girls_3": 34.72,
  "Boys_3": 38.69,
  "Overall_3": 37.1
 },
 {
  "Location": "JUNAGADH",
  "Index": 72,
  "Social Category": "OBC",
  "Girls_1": 54.65,
  "Boys_1": 53.55,
  "Overall_1": 54.08,
  "Girls_2": 56.33,
  "Boys_2": 53.35,
  "Overall_2": 54.75,
  "Girls_3": 56.74,
  "Boys_3": 59.34,
  "Overall_3": 58.25
 },
 {
  "Location": "JUNAGADH",
  "Index": 73,
  "Social Category": "SC",
  "Girls_1": 47.14,
  "Boys_1": 47.87,
  "Overall_1": 47.53,
  "Girls_2": 46.02,
  "Boys_2": 40.86,
  "Overall_2": 43.33,
  "Girls_3": 50.88,
  "Boys_3": 51.17,
  "Overall_3": 51.04
 },
 {
  "Location": "JUNAGADH",
  "Index": 74,
  "Social Category": "ST",
  "Girls_1": 48.12,
  "Boys_1": 44.82,
  "Overall_1": 46.27,
  "Girls_2": 51.03,
  "Boys_2": 43.94,
  "Overall_2": 47.07,
  "Girls_3": 60.98,
  "Boys_3": 44.04,
  "Overall_3": 51.59
 },
 {
  "Location": "JUNAGADH",
  "Index": 75,
  "Social Category": "Overall",
  "Girls_1": 50.94,
  "Boys_1": 49.21,
  "Overall_1": 50.02,
  "Girls_2": 52.1,
  "Boys_2": 47.75,
  "Overall_2": 49.77,
  "Girls_3": 51.87,
  "Boys_3": 53.86,
  "Overall_3": 53.03
 },
 {
  "Location": "KACHCHH",
  "Index": 76,
  "Social Category": "General",
  "Girls_1": 0.4,
  "Boys_1": 0.89,
  "Overall_1": 0.66,
  "Girls_2": 9.52,
  "Boys_2": 6.36,
  "Overall_2": 7.78,
  "Girls_3": 18.21,
  "Boys_3": 29.31,
  "Overall_3": 24.77
 },
 {
  "Location": "KACHCHH",
  "Index": 77,
  "Social Category": "OBC",
  "Girls_1": 1.95,
  "Boys_1": 0.93,
  "Overall_1": 1.41,
  "Girls_2": 14.48,
  "Boys_2": 8.69,
  "Overall_2": 11.2,
  "Girls_3": 20.66,
  "Boys_3": 37.82,
  "Overall_3": 32.55
 },
 {
  "Location": "KACHCHH",
  "Index": 78,
  "Social Category": "SC",
  "Girls_1": 0,
  "Boys_1": 0,
  "Overall_1": 0,
  "Girls_2": 11.76,
  "Boys_2": 4.42,
  "Overall_2": 7.78,
  "Girls_3": 27.26,
  "Boys_3": 39.14,
  "Overall_3": 35.26
 },
 {
  "Location": "KACHCHH",
  "Index": 79,
  "Social Category": "ST",
  "Girls_1": 2.1,
  "Boys_1": 4.5,
  "Overall_1": 3.5,
  "Girls_2": 13.87,
  "Boys_2": 12.08,
  "Overall_2": 12.78,
  "Girls_3": 20,
  "Boys_3": 42.11,
  "Overall_3": 35.17
 },
 {
  "Location": "KACHCHH",
  "Index": 80,
  "Social Category": "Overall",
  "Girls_1": 1.06,
  "Boys_1": 0.72,
  "Overall_1": 0.88,
  "Girls_2": 12.08,
  "Boys_2": 7.23,
  "Overall_2": 9.38,
  "Girls_3": 20.27,
  "Boys_3": 34.37,
  "Overall_3": 29.32
 },
 {
  "Location": "KHEDA",
  "Index": 81,
  "Social Category": "General",
  "Girls_1": 8.45,
  "Boys_1": 6.56,
  "Overall_1": 7.43,
  "Girls_2": 8.55,
  "Boys_2": 7.16,
  "Overall_2": 7.77,
  "Girls_3": 22.46,
  "Boys_3": 26.92,
  "Overall_3": 25.16
 },
 {
  "Location": "KHEDA",
  "Index": 82,
  "Social Category": "OBC",
  "Girls_1": 12.04,
  "Boys_1": 11.63,
  "Overall_1": 11.83,
  "Girls_2": 19.38,
  "Boys_2": 14.56,
  "Overall_2": 16.77,
  "Girls_3": 41.76,
  "Boys_3": 38.54,
  "Overall_3": 39.75
 },
 {
  "Location": "KHEDA",
  "Index": 83,
  "Social Category": "SC",
  "Girls_1": 15.84,
  "Boys_1": 15.04,
  "Overall_1": 15.41,
  "Girls_2": 22.36,
  "Boys_2": 18.01,
  "Overall_2": 20.03,
  "Girls_3": 29.75,
  "Boys_3": 35.36,
  "Overall_3": 33.03
 },
 {
  "Location": "KHEDA",
  "Index": 84,
  "Social Category": "ST",
  "Girls_1": 11.34,
  "Boys_1": 16.23,
  "Overall_1": 14.16,
  "Girls_2": 20.58,
  "Boys_2": 22.1,
  "Overall_2": 21.51,
  "Girls_3": 33.76,
  "Boys_3": 43.41,
  "Overall_3": 39.84
 },
 {
  "Location": "KHEDA",
  "Index": 85,
  "Social Category": "Overall",
  "Girls_1": 11.66,
  "Boys_1": 11.16,
  "Overall_1": 11.39,
  "Girls_2": 17.87,
  "Boys_2": 13.71,
  "Overall_2": 15.59,
  "Girls_3": 36.95,
  "Boys_3": 36.28,
  "Overall_3": 36.53
 },
 {
  "Location": "MAHESANA",
  "Index": 86,
  "Social Category": "General",
  "Girls_1": 1.65,
  "Boys_1": 2.59,
  "Overall_1": 2.2,
  "Girls_2": 1.31,
  "Boys_2": 3.12,
  "Overall_2": 2.41,
  "Girls_3": 6.56,
  "Boys_3": 14.08,
  "Overall_3": 11.05
 },
 {
  "Location": "MAHESANA",
  "Index": 87,
  "Social Category": "OBC",
  "Girls_1": 0.4,
  "Boys_1": 0,
  "Overall_1": 0,
  "Girls_2": 7.11,
  "Boys_2": 0.8,
  "Overall_2": 3.51,
  "Girls_3": 22.49,
  "Boys_3": 26.6,
  "Overall_3": 25.13
 },
 {
  "Location": "MAHESANA",
  "Index": 88,
  "Social Category": "SC",
  "Girls_1": 2.35,
  "Boys_1": 1.04,
  "Overall_1": 1.65,
  "Girls_2": 2.91,
  "Boys_2": 0,
  "Overall_2": 1.25,
  "Girls_3": 15.29,
  "Boys_3": 21.6,
  "Overall_3": 18.93
 },
 {
  "Location": "MAHESANA",
  "Index": 89,
  "Social Category": "ST",
  "Girls_1": 3.11,
  "Boys_1": 1.84,
  "Overall_1": 2.41,
  "Girls_2": 6.01,
  "Boys_2": 0,
  "Overall_2": 0,
  "Girls_3": 0,
  "Boys_3": 19.85,
  "Overall_3": 12.56
 },
 {
  "Location": "MAHESANA",
  "Index": 90,
  "Social Category": "Overall",
  "Girls_1": 0.81,
  "Boys_1": 0.07,
  "Overall_1": 0.41,
  "Girls_2": 5.44,
  "Boys_2": 1.14,
  "Overall_2": 2.96,
  "Girls_3": 16.48,
  "Boys_3": 22.53,
  "Overall_3": 20.25
 },
 {
  "Location": "MAHISAGAR",
  "Index": 91,
  "Social Category": "General",
  "Girls_1": 0,
  "Boys_1": 0,
  "Overall_1": 0,
  "Girls_2": 0,
  "Boys_2": 0,
  "Overall_2": 0,
  "Girls_3": 0,
  "Boys_3": 0,
  "Overall_3": 0
 },
 {
  "Location": "MAHISAGAR",
  "Index": 92,
  "Social Category": "OBC",
  "Girls_1": 0,
  "Boys_1": 0,
  "Overall_1": 0,
  "Girls_2": 0,
  "Boys_2": 0,
  "Overall_2": 0,
  "Girls_3": 0,
  "Boys_3": 0,
  "Overall_3": 0
 },
 {
  "Location": "MAHISAGAR",
  "Index": 93,
  "Social Category": "SC",
  "Girls_1": 0,
  "Boys_1": 0,
  "Overall_1": 0,
  "Girls_2": 0,
  "Boys_2": 0,
  "Overall_2": 0,
  "Girls_3": 0,
  "Boys_3": 0,
  "Overall_3": 0
 },
 {
  "Location": "MAHISAGAR",
  "Index": 94,
  "Social Category": "ST",
  "Girls_1": 0,
  "Boys_1": 0,
  "Overall_1": 0,
  "Girls_2": 0,
  "Boys_2": 0,
  "Overall_2": 0,
  "Girls_3": 0,
  "Boys_3": 0,
  "Overall_3": 0
 },
 {
  "Location": "MAHISAGAR",
  "Index": 95,
  "Social Category": "Overall",
  "Girls_1": 0,
  "Boys_1": 0,
  "Overall_1": 0,
  "Girls_2": 0,
  "Boys_2": 0,
  "Overall_2": 0,
  "Girls_3": 0,
  "Boys_3": 0,
  "Overall_3": 0
 },
 {
  "Location": "MORBI",
  "Index": 96,
  "Social Category": "General",
  "Girls_1": 0,
  "Boys_1": 0,
  "Overall_1": 0,
  "Girls_2": 0,
  "Boys_2": 0,
  "Overall_2": 0,
  "Girls_3": 0,
  "Boys_3": 0,
  "Overall_3": 0
 },
 {
  "Location": "MORBI",
  "Index": 97,
  "Social Category": "OBC",
  "Girls_1": 0,
  "Boys_1": 0,
  "Overall_1": 0,
  "Girls_2": 0,
  "Boys_2": 0,
  "Overall_2": 0,
  "Girls_3": 0,
  "Boys_3": 0,
  "Overall_3": 0
 },
 {
  "Location": "MORBI",
  "Index": 98,
  "Social Category": "SC",
  "Girls_1": 0,
  "Boys_1": 0,
  "Overall_1": 0,
  "Girls_2": 0,
  "Boys_2": 0,
  "Overall_2": 0,
  "Girls_3": 0,
  "Boys_3": 0,
  "Overall_3": 0
 },
 {
  "Location": "MORBI",
  "Index": 99,
  "Social Category": "ST",
  "Girls_1": 0,
  "Boys_1": 0,
  "Overall_1": 0,
  "Girls_2": 0,
  "Boys_2": 0,
  "Overall_2": 0,
  "Girls_3": 0,
  "Boys_3": 0,
  "Overall_3": 0
 },
 {
  "Location": "MORBI",
  "Index": 100,
  "Social Category": "Overall",
  "Girls_1": 0,
  "Boys_1": 0,
  "Overall_1": 0,
  "Girls_2": 0,
  "Boys_2": 0,
  "Overall_2": 0,
  "Girls_3": 0,
  "Boys_3": 0,
  "Overall_3": 0
 },
 {
  "Location": "NARMADA",
  "Index": 101,
  "Social Category": "General",
  "Girls_1": 8.45,
  "Boys_1": 6.94,
  "Overall_1": 7.66,
  "Girls_2": 13.4,
  "Boys_2": 10.54,
  "Overall_2": 11.92,
  "Girls_3": 30.18,
  "Boys_3": 39.79,
  "Overall_3": 35.84
 },
 {
  "Location": "NARMADA",
  "Index": 102,
  "Social Category": "OBC",
  "Girls_1": 0.34,
  "Boys_1": 0,
  "Overall_1": 0,
  "Girls_2": 9.43,
  "Boys_2": 2.44,
  "Overall_2": 5.83,
  "Girls_3": 25.89,
  "Boys_3": 16.02,
  "Overall_3": 20.54
 },
 {
  "Location": "NARMADA",
  "Index": 103,
  "Social Category": "SC",
  "Girls_1": 8.53,
  "Boys_1": 25.15,
  "Overall_1": 17.38,
  "Girls_2": 0,
  "Boys_2": 18.08,
  "Overall_2": 9.26,
  "Girls_3": 0,
  "Boys_3": 0,
  "Overall_3": 0
 },
 {
  "Location": "NARMADA",
  "Index": 104,
  "Social Category": "ST",
  "Girls_1": 0.43,
  "Boys_1": 1.28,
  "Overall_1": 0.87,
  "Girls_2": 9.54,
  "Boys_2": 7.43,
  "Overall_2": 8.46,
  "Girls_3": 25.69,
  "Boys_3": 29.63,
  "Overall_3": 27.75
 },
 {
  "Location": "NARMADA",
  "Index": 105,
  "Social Category": "Overall",
  "Girls_1": 0.99,
  "Boys_1": 1.55,
  "Overall_1": 1.27,
  "Girls_2": 9.63,
  "Boys_2": 7.48,
  "Overall_2": 8.51,
  "Girls_3": 24.73,
  "Boys_3": 28.24,
  "Overall_3": 26.59
 },
 {
  "Location": "NAVSARI",
  "Index": 106,
  "Social Category": "General",
  "Girls_1": 2.56,
  "Boys_1": 2.01,
  "Overall_1": 2.26,
  "Girls_2": 4.85,
  "Boys_2": 3.48,
  "Overall_2": 4.09,
  "Girls_3": 15.58,
  "Boys_3": 16.82,
  "Overall_3": 16.26
 },
 {
  "Location": "NAVSARI",
  "Index": 107,
  "Social Category": "OBC",
  "Girls_1": 0,
  "Boys_1": 0,
  "Overall_1": 0,
  "Girls_2": 0.2,
  "Boys_2": 0,
  "Overall_2": 0,
  "Girls_3": 14.82,
  "Boys_3": 21.26,
  "Overall_3": 18.38
 },
 {
  "Location": "NAVSARI",
  "Index": 108,
  "Social Category": "SC",
  "Girls_1": 0,
  "Boys_1": 0,
  "Overall_1": 0,
  "Girls_2": 0,
  "Boys_2": 0,
  "Overall_2": 0,
  "Girls_3": 25.98,
  "Boys_3": 12.43,
  "Overall_3": 18.73
 },
 {
  "Location": "NAVSARI",
  "Index": 109,
  "Social Category": "ST",
  "Girls_1": 1.41,
  "Boys_1": 2.44,
  "Overall_1": 1.94,
  "Girls_2": 2.79,
  "Boys_2": 0,
  "Overall_2": 1.12,
  "Girls_3": 17.64,
  "Boys_3": 25.79,
  "Overall_3": 21.93
 },
 {
  "Location": "NAVSARI",
  "Index": 110,
  "Social Category": "Overall",
  "Girls_1": 0.67,
  "Boys_1": 0.82,
  "Overall_1": 0.75,
  "Girls_2": 2.31,
  "Boys_2": 0,
  "Overall_2": 1.08,
  "Girls_3": 16.8,
  "Boys_3": 22.56,
  "Overall_3": 19.89
 },
 {
  "Location": "PANCH MAHALS",
  "Index": 111,
  "Social Category": "General",
  "Girls_1": 48.99,
  "Boys_1": 45.17,
  "Overall_1": 46.95,
  "Girls_2": 48.19,
  "Boys_2": 45.08,
  "Overall_2": 46.48,
  "Girls_3": 55.6,
  "Boys_3": 55.13,
  "Overall_3": 55.34
 },
 {
  "Location": "PANCH MAHALS",
  "Index": 112,
  "Social Category": "OBC",
  "Girls_1": 19.37,
  "Boys_1": 20.63,
  "Overall_1": 20.03,
  "Girls_2": 23.06,
  "Boys_2": 22.17,
  "Overall_2": 22.58,
  "Girls_3": 35.94,
  "Boys_3": 37.64,
  "Overall_3": 36.9
 },
 {
  "Location": "PANCH MAHALS",
  "Index": 113,
  "Social Category": "SC",
  "Girls_1": 33.25,
  "Boys_1": 37.04,
  "Overall_1": 35.27,
  "Girls_2": 37.86,
  "Boys_2": 35.96,
  "Overall_2": 36.82,
  "Girls_3": 53.22,
  "Boys_3": 55.29,
  "Overall_3": 54.37
 },
 {
  "Location": "PANCH MAHALS",
  "Index": 114,
  "Social Category": "ST",
  "Girls_1": 48.36,
  "Boys_1": 47.72,
  "Overall_1": 48.03,
  "Girls_2": 56.53,
  "Boys_2": 55.52,
  "Overall_2": 56,
  "Girls_3": 67.59,
  "Boys_3": 67.58,
  "Overall_3": 67.58
 },
 {
  "Location": "PANCH MAHALS",
  "Index": 115,
  "Social Category": "Overall",
  "Girls_1": 32.57,
  "Boys_1": 32.8,
  "Overall_1": 32.69,
  "Girls_2": 36.56,
  "Boys_2": 35.19,
  "Overall_2": 35.83,
  "Girls_3": 48.47,
  "Boys_3": 48.4,
  "Overall_3": 48.43
 },
 {
  "Location": "PATAN",
  "Index": 116,
  "Social Category": "General",
  "Girls_1": 0.04,
  "Boys_1": 0.1,
  "Overall_1": 0.07,
  "Girls_2": 5.9,
  "Boys_2": 2.38,
  "Overall_2": 3.92,
  "Girls_3": 18.49,
  "Boys_3": 6.61,
  "Overall_3": 11.64
 },
 {
  "Location": "PATAN",
  "Index": 117,
  "Social Category": "OBC",
  "Girls_1": 0.8,
  "Boys_1": 0.43,
  "Overall_1": 0.6,
  "Girls_2": 11.06,
  "Boys_2": 4.61,
  "Overall_2": 7.39,
  "Girls_3": 31.81,
  "Boys_3": 16.96,
  "Overall_3": 22.4
 },
 {
  "Location": "PATAN",
  "Index": 118,
  "Social Category": "SC",
  "Girls_1": 0,
  "Boys_1": 1.59,
  "Overall_1": 0.09,
  "Girls_2": 6.53,
  "Boys_2": 2.32,
  "Overall_2": 4.22,
  "Girls_3": 20.87,
  "Boys_3": 17.67,
  "Overall_3": 19.06
 },
 {
  "Location": "PATAN",
  "Index": 119,
  "Social Category": "ST",
  "Girls_1": 14.62,
  "Boys_1": 14.17,
  "Overall_1": 14.37,
  "Girls_2": 30.03,
  "Boys_2": 7.88,
  "Overall_2": 17.12,
  "Girls_3": 55.06,
  "Boys_3": 37.03,
  "Overall_3": 44.58
 },
 {
  "Location": "PATAN",
  "Index": 120,
  "Social Category": "Overall",
  "Girls_1": 0.68,
  "Boys_1": 0.7,
  "Overall_1": 0.7,
  "Girls_2": 10.03,
  "Boys_2": 4.08,
  "Overall_2": 6.66,
  "Girls_3": 27.71,
  "Boys_3": 15.31,
  "Overall_3": 20.11
 },
 {
  "Location": "PORBANDAR",
  "Index": 121,
  "Social Category": "General",
  "Girls_1": 4.84,
  "Boys_1": 0.62,
  "Overall_1": 2.52,
  "Girls_2": 2.96,
  "Boys_2": 2.22,
  "Overall_2": 2.53,
  "Girls_3": 18.2,
  "Boys_3": 27.1,
  "Overall_3": 23.53
 },
 {
  "Location": "PORBANDAR",
  "Index": 122,
  "Social Category": "OBC",
  "Girls_1": 0.16,
  "Boys_1": 1.52,
  "Overall_1": 0.88,
  "Girls_2": 10.14,
  "Boys_2": 6.89,
  "Overall_2": 8.45,
  "Girls_3": 19.37,
  "Boys_3": 28.65,
  "Overall_3": 24.62
 },
 {
  "Location": "PORBANDAR",
  "Index": 123,
  "Social Category": "SC",
  "Girls_1": 6.36,
  "Boys_1": 3.13,
  "Overall_1": 4.74,
  "Girls_2": 8.32,
  "Boys_2": 6.05,
  "Overall_2": 7.16,
  "Girls_3": 13.8,
  "Boys_3": 30.44,
  "Overall_3": 23.04
 },
 {
  "Location": "PORBANDAR",
  "Index": 124,
  "Social Category": "ST",
  "Girls_1": 9.93,
  "Boys_1": 11.49,
  "Overall_1": 10.82,
  "Girls_2": 30.71,
  "Boys_2": 15.36,
  "Overall_2": 22.32,
  "Girls_3": 50,
  "Boys_3": 37.78,
  "Overall_3": 42.57
 },
 {
  "Location": "PORBANDAR",
  "Index": 125,
  "Social Category": "Overall",
  "Girls_1": 1.47,
  "Boys_1": 1.82,
  "Overall_1": 1.65,
  "Girls_2": 9.51,
  "Boys_2": 6.35,
  "Overall_2": 7.85,
  "Girls_3": 19.08,
  "Boys_3": 28.73,
  "Overall_3": 24.59
 },
 {
  "Location": "RAJKOT",
  "Index": 126,
  "Social Category": "General",
  "Girls_1": 24.12,
  "Boys_1": 23.57,
  "Overall_1": 23.81,
  "Girls_2": 22.26,
  "Boys_2": 20.78,
  "Overall_2": 21.41,
  "Girls_3": 26.1,
  "Boys_3": 29.51,
  "Overall_3": 28.09
 },
 {
  "Location": "RAJKOT",
  "Index": 127,
  "Social Category": "OBC",
  "Girls_1": 22.04,
  "Boys_1": 19.85,
  "Overall_1": 20.88,
  "Girls_2": 29.32,
  "Boys_2": 22.34,
  "Overall_2": 25.47,
  "Girls_3": 32.22,
  "Boys_3": 36.71,
  "Overall_3": 35.01
 },
 {
  "Location": "RAJKOT",
  "Index": 128,
  "Social Category": "SC",
  "Girls_1": 20.46,
  "Boys_1": 19.45,
  "Overall_1": 19.93,
  "Girls_2": 24.54,
  "Boys_2": 20.71,
  "Overall_2": 22.48,
  "Girls_3": 38.84,
  "Boys_3": 44.44,
  "Overall_3": 41.95
 },
 {
  "Location": "RAJKOT",
  "Index": 129,
  "Social Category": "ST",
  "Girls_1": 15.41,
  "Boys_1": 18.03,
  "Overall_1": 17.02,
  "Girls_2": 21.09,
  "Boys_2": 24.52,
  "Overall_2": 23.19,
  "Girls_3": 19.52,
  "Boys_3": 42.67,
  "Overall_3": 34.52
 },
 {
  "Location": "RAJKOT",
  "Index": 130,
  "Social Category": "Overall",
  "Girls_1": 22.39,
  "Boys_1": 21.01,
  "Overall_1": 21.63,
  "Girls_2": 26.43,
  "Boys_2": 21.67,
  "Overall_2": 23.76,
  "Girls_3": 29.96,
  "Boys_3": 34.32,
  "Overall_3": 32.57
 },
 {
  "Location": "SABAR KANTHA",
  "Index": 131,
  "Social Category": "General",
  "Girls_1": 28.91,
  "Boys_1": 28.85,
  "Overall_1": 28.88,
  "Girls_2": 29.5,
  "Boys_2": 29.99,
  "Overall_2": 29.78,
  "Girls_3": 33.29,
  "Boys_3": 38.08,
  "Overall_3": 36.1
 },
 {
  "Location": "SABAR KANTHA",
  "Index": 132,
  "Social Category": "OBC",
  "Girls_1": 49,
  "Boys_1": 48.39,
  "Overall_1": 48.68,
  "Girls_2": 52.99,
  "Boys_2": 49.11,
  "Overall_2": 50.87,
  "Girls_3": 61.82,
  "Boys_3": 58.11,
  "Overall_3": 59.65
 },
 {
  "Location": "SABAR KANTHA",
  "Index": 133,
  "Social Category": "SC",
  "Girls_1": 30.13,
  "Boys_1": 29.85,
  "Overall_1": 29.98,
  "Girls_2": 30.89,
  "Boys_2": 29.91,
  "Overall_2": 30.35,
  "Girls_3": 34.01,
  "Boys_3": 35.52,
  "Overall_3": 34.85
 },
 {
  "Location": "SABAR KANTHA",
  "Index": 134,
  "Social Category": "ST",
  "Girls_1": 37.2,
  "Boys_1": 36.41,
  "Overall_1": 36.79,
  "Girls_2": 45.77,
  "Boys_2": 45.36,
  "Overall_2": 45.55,
  "Girls_3": 58.88,
  "Boys_3": 58.74,
  "Overall_3": 58.81
 },
 {
  "Location": "SABAR KANTHA",
  "Index": 135,
  "Social Category": "Overall",
  "Girls_1": 42.52,
  "Boys_1": 41.77,
  "Overall_1": 42.12,
  "Girls_2": 47.17,
  "Boys_2": 44.61,
  "Overall_2": 45.77,
  "Girls_3": 54.94,
  "Boys_3": 53.55,
  "Overall_3": 54.14
 },
 {
  "Location": "SURAT",
  "Index": 136,
  "Social Category": "General",
  "Girls_1": 0,
  "Boys_1": 0,
  "Overall_1": 0,
  "Girls_2": 0.97,
  "Boys_2": 0,
  "Overall_2": 0,
  "Girls_3": 13.67,
  "Boys_3": 16.15,
  "Overall_3": 15.1
 },
 {
  "Location": "SURAT",
  "Index": 137,
  "Social Category": "OBC",
  "Girls_1": 0,
  "Boys_1": 0,
  "Overall_1": 0,
  "Girls_2": 2.53,
  "Boys_2": 0.94,
  "Overall_2": 1.63,
  "Girls_3": 12.03,
  "Boys_3": 22.35,
  "Overall_3": 18.14
 },
 {
  "Location": "SURAT",
  "Index": 138,
  "Social Category": "SC",
  "Girls_1": 1.9,
  "Boys_1": 0.28,
  "Overall_1": 1.04,
  "Girls_2": 9.32,
  "Boys_2": 8.55,
  "Overall_2": 8.89,
  "Girls_3": 21.34,
  "Boys_3": 33.66,
  "Overall_3": 28.49
 },
 {
  "Location": "SURAT",
  "Index": 139,
  "Social Category": "ST",
  "Girls_1": 2.46,
  "Boys_1": 1.94,
  "Overall_1": 2.19,
  "Girls_2": 8.97,
  "Boys_2": 8.28,
  "Overall_2": 8.61,
  "Girls_3": 26.87,
  "Boys_3": 34.9,
  "Overall_3": 31.11
 },
 {
  "Location": "SURAT",
  "Index": 140,
  "Social Category": "Overall",
  "Girls_1": 0,
  "Boys_1": 0,
  "Overall_1": 0,
  "Girls_2": 3.17,
  "Boys_2": 0.68,
  "Overall_2": 1.78,
  "Girls_3": 15.81,
  "Boys_3": 20.96,
  "Overall_3": 18.77
 },
 {
  "Location": "SURENDRANAGAR",
  "Index": 141,
  "Social Category": "General",
  "Girls_1": 14.85,
  "Boys_1": 14.21,
  "Overall_1": 14.48,
  "Girls_2": 16.05,
  "Boys_2": 15.37,
  "Overall_2": 15.64,
  "Girls_3": 26.65,
  "Boys_3": 27.01,
  "Overall_3": 26.86
 },
 {
  "Location": "SURENDRANAGAR",
  "Index": 142,
  "Social Category": "OBC",
  "Girls_1": 11.17,
  "Boys_1": 10.79,
  "Overall_1": 10.96,
  "Girls_2": 24.64,
  "Boys_2": 18.75,
  "Overall_2": 21.35,
  "Girls_3": 34.56,
  "Boys_3": 35.28,
  "Overall_3": 35.04
 },
 {
  "Location": "SURENDRANAGAR",
  "Index": 143,
  "Social Category": "SC",
  "Girls_1": 12.22,
  "Boys_1": 12.22,
  "Overall_1": 12.22,
  "Girls_2": 16.34,
  "Boys_2": 14.43,
  "Overall_2": 15.31,
  "Girls_3": 33.41,
  "Boys_3": 27.56,
  "Overall_3": 30.06
 },
 {
  "Location": "SURENDRANAGAR",
  "Index": 144,
  "Social Category": "ST",
  "Girls_1": 32.33,
  "Boys_1": 31.81,
  "Overall_1": 32.02,
  "Girls_2": 45.16,
  "Boys_2": 33.42,
  "Overall_2": 37.53,
  "Girls_3": 54.69,
  "Boys_3": 45.67,
  "Overall_3": 48.1
 },
 {
  "Location": "SURENDRANAGAR",
  "Index": 145,
  "Social Category": "Overall",
  "Girls_1": 12.19,
  "Boys_1": 12.02,
  "Overall_1": 12.1,
  "Girls_2": 23,
  "Boys_2": 18.18,
  "Overall_2": 20.29,
  "Girls_3": 32.7,
  "Boys_3": 33.04,
  "Overall_3": 32.91
 },
 {
  "Location": "TAPI",
  "Index": 146,
  "Social Category": "General",
  "Girls_1": 2.93,
  "Boys_1": 6.42,
  "Overall_1": 4.75,
  "Girls_2": 1,
  "Boys_2": 15.75,
  "Overall_2": 8.99,
  "Girls_3": 1.13,
  "Boys_3": 22.11,
  "Overall_3": 12.1
 },
 {
  "Location": "TAPI",
  "Index": 147,
  "Social Category": "OBC",
  "Girls_1": 6.45,
  "Boys_1": 8.71,
  "Overall_1": 7.63,
  "Girls_2": 11.28,
  "Boys_2": 8.59,
  "Overall_2": 9.84,
  "Girls_3": 23.7,
  "Boys_3": 27.74,
  "Overall_3": 26.03
 },
 {
  "Location": "TAPI",
  "Index": 148,
  "Social Category": "SC",
  "Girls_1": 29.73,
  "Boys_1": 35.7,
  "Overall_1": 32.96,
  "Girls_2": 43.16,
  "Boys_2": 31.03,
  "Overall_2": 36.84,
  "Girls_3": 38.99,
  "Boys_3": 48.92,
  "Overall_3": 44.36
 },
 {
  "Location": "TAPI",
  "Index": 149,
  "Social Category": "ST",
  "Girls_1": 0,
  "Boys_1": 0.02,
  "Overall_1": 0,
  "Girls_2": 9.66,
  "Boys_2": 9.16,
  "Overall_2": 9.41,
  "Girls_3": 17.88,
  "Boys_3": 17.32,
  "Overall_3": 17.61
 },
 {
  "Location": "TAPI",
  "Index": 150,
  "Social Category": "Overall",
  "Girls_1": 0.81,
  "Boys_1": 1.59,
  "Overall_1": 1.21,
  "Girls_2": 9.85,
  "Boys_2": 10,
  "Overall_2": 9.93,
  "Girls_3": 17.7,
  "Boys_3": 19.38,
  "Overall_3": 18.55
 },
 {
  "Location": "DANG",
  "Index": 151,
  "Social Category": "General",
  "Girls_1": 0,
  "Boys_1": 0,
  "Overall_1": 0,
  "Girls_2": 0,
  "Boys_2": 0,
  "Overall_2": 0,
  "Girls_3": 86.23,
  "Boys_3": 89.44,
  "Overall_3": 87.89
 },
 {
  "Location": "DANG",
  "Index": 152,
  "Social Category": "OBC",
  "Girls_1": 0,
  "Boys_1": 0,
  "Overall_1": 0,
  "Girls_2": 0,
  "Boys_2": 0,
  "Overall_2": 0,
  "Girls_3": 0,
  "Boys_3": 20.83,
  "Overall_3": 9.63
 },
 {
  "Location": "DANG",
  "Index": 153,
  "Social Category": "SC",
  "Girls_1": 0,
  "Boys_1": 0,
  "Overall_1": 0,
  "Girls_2": 0,
  "Boys_2": 0,
  "Overall_2": 0,
  "Girls_3": 11.77,
  "Boys_3": 12.5,
  "Overall_3": 12
 },
 {
  "Location": "DANG",
  "Index": 154,
  "Social Category": "ST",
  "Girls_1": 4.65,
  "Boys_1": 4.66,
  "Overall_1": 4.65,
  "Girls_2": 12.4,
  "Boys_2": 11.92,
  "Overall_2": 12.16,
  "Girls_3": 8.81,
  "Boys_3": 8.67,
  "Overall_3": 8.74
 },
 {
  "Location": "DANG",
  "Index": 155,
  "Social Category": "Overall",
  "Girls_1": 4.33,
  "Boys_1": 4.39,
  "Overall_1": 4.36,
  "Girls_2": 11.55,
  "Boys_2": 11.42,
  "Overall_2": 11.48,
  "Girls_3": 13.01,
  "Boys_3": 13.89,
  "Overall_3": 13.45
 },
 {
  "Location": "VADODARA",
  "Index": 156,
  "Social Category": "General",
  "Girls_1": 2.17,
  "Boys_1": 3.13,
  "Overall_1": 2.69,
  "Girls_2": 6.08,
  "Boys_2": 3.07,
  "Overall_2": 4.39,
  "Girls_3": 20.21,
  "Boys_3": 27.65,
  "Overall_3": 24.58
 },
 {
  "Location": "VADODARA",
  "Index": 157,
  "Social Category": "OBC",
  "Girls_1": 11.98,
  "Boys_1": 10.6,
  "Overall_1": 11.25,
  "Girls_2": 21.15,
  "Boys_2": 13.49,
  "Overall_2": 16.91,
  "Girls_3": 37.42,
  "Boys_3": 44.63,
  "Overall_3": 41.8
 },
 {
  "Location": "VADODARA",
  "Index": 158,
  "Social Category": "SC",
  "Girls_1": 10.67,
  "Boys_1": 8.84,
  "Overall_1": 9.68,
  "Girls_2": 9.81,
  "Boys_2": 11.01,
  "Overall_2": 10.49,
  "Girls_3": 28.43,
  "Boys_3": 36.59,
  "Overall_3": 33.03
 },
 {
  "Location": "VADODARA",
  "Index": 159,
  "Social Category": "ST",
  "Girls_1": 72.11,
  "Boys_1": 71.13,
  "Overall_1": 71.6,
  "Girls_2": 71.1,
  "Boys_2": 67.81,
  "Overall_2": 69.33,
  "Girls_3": 77.5,
  "Boys_3": 77.09,
  "Overall_3": 77.27
 },
 {
  "Location": "VADODARA",
  "Index": 160,
  "Social Category": "Overall",
  "Girls_1": 28.48,
  "Boys_1": 26.96,
  "Overall_1": 27.67,
  "Girls_2": 28.45,
  "Boys_2": 23.4,
  "Overall_2": 25.65,
  "Girls_3": 37.73,
  "Boys_3": 42.76,
  "Overall_3": 40.67
 },
 {
  "Location": "VALSAD",
  "Index": 161,
  "Social Category": "General",
  "Girls_1": 13.24,
  "Boys_1": 16.87,
  "Overall_1": 15.25,
  "Girls_2": 10.65,
  "Boys_2": 16.66,
  "Overall_2": 14.09,
  "Girls_3": 19.49,
  "Boys_3": 29.02,
  "Overall_3": 24.89
 },
 {
  "Location": "VALSAD",
  "Index": 162,
  "Social Category": "OBC",
  "Girls_1": 0,
  "Boys_1": 0,
  "Overall_1": 0,
  "Girls_2": 0,
  "Boys_2": 0,
  "Overall_2": 0,
  "Girls_3": 7.41,
  "Boys_3": 2.31,
  "Overall_3": 4.7
 },
 {
  "Location": "VALSAD",
  "Index": 163,
  "Social Category": "SC",
  "Girls_1": 0,
  "Boys_1": 0,
  "Overall_1": 0,
  "Girls_2": 0,
  "Boys_2": 0,
  "Overall_2": 0,
  "Girls_3": 14.54,
  "Boys_3": 8.27,
  "Overall_3": 11.44
 },
 {
  "Location": "VALSAD",
  "Index": 164,
  "Social Category": "ST",
  "Girls_1": 2.23,
  "Boys_1": 2.36,
  "Overall_1": 2.3,
  "Girls_2": 6.62,
  "Boys_2": 5.69,
  "Overall_2": 6.14,
  "Girls_3": 16.24,
  "Boys_3": 17.18,
  "Overall_3": 16.73
 },
 {
  "Location": "VALSAD",
  "Index": 165,
  "Social Category": "Overall",
  "Girls_1": 2.96,
  "Boys_1": 3.39,
  "Overall_1": 3.19,
  "Girls_2": 5.9,
  "Boys_2": 5.1,
  "Overall_2": 5.48,
  "Girls_3": 14.98,
  "Boys_3": 16.53,
  "Overall_3": 15.8
 },
 {
  "Location": "Gujarat",
  "Index": 166,
  "Social Category": "General",
  "Girls_1": 1.15,
  "Boys_1": 0.81,
  "Overall_1": 0.97,
  "Girls_2": 4.27,
  "Boys_2": 1.55,
  "Overall_2": 2.74,
  "Girls_3": 15.23,
  "Boys_3": 18.76,
  "Overall_3": 17.28
 },
 {
  "Location": "Gujarat",
  "Index": 167,
  "Social Category": "SC",
  "Girls_1": 0.53,
  "Boys_1": 0,
  "Overall_1": 0.18,
  "Girls_2": 5.56,
  "Boys_2": 1.62,
  "Overall_2": 3.43,
  "Girls_3": 21.78,
  "Boys_3": 24.39,
  "Overall_3": 23.26
 },
 {
  "Location": "Gujarat",
  "Index": 168,
  "Social Category": "ST",
  "Girls_1": 3.34,
  "Boys_1": 3.33,
  "Overall_1": 3.34,
  "Girls_2": 10.07,
  "Boys_2": 8.51,
  "Overall_2": 9.24,
  "Girls_3": 21.27,
  "Boys_3": 25.1,
  "Overall_3": 23.32
 },
 {
  "Location": "Gujarat",
  "Index": 169,
  "Social Category": "OBC",
  "Girls_1": 0.26,
  "Boys_1": 0,
  "Overall_1": 0,
  "Girls_2": 9.71,
  "Boys_2": 3.34,
  "Overall_2": 6.2,
  "Girls_3": 22.42,
  "Boys_3": 24.73,
  "Overall_3": 23.85
 },
 {
  "Location": "_Overall_",
  "Index": 170,
  "Social Category": "Overall",
  "Girls_1": 1.07,
  "Boys_1": 0.5,
  "Overall_1": 0.76,
  "Girls_2": 8.04,
  "Boys_2": 3.51,
  "Overall_2": 5.55,
  "Girls_3": 19.81,
  "Boys_3": 22.85,
  "Overall_3": 21.61
 }
]